{
  "brand": "Wendy's",
  "searches": {
    "positioning": {
      "query": "Wendy's brand positioning strategy marketing Canadian QSR 2025 2026",
      "count": 5,
      "results": [
        {
          "title": "Wendy's Calls 2026 a Rebuilding Year as Sales Slide and ...",
          "url": "https://www.qsrmagazine.com/story/wendys-calls-2026-a-rebuilding-year-as-sales-slide-and-closures-accelerate/",
          "snippet": "Feb 13, 2026 \u2014 Wendy's interim CEO Ken Cook made it clear to investors Friday that 2026 will be a rebuilding year for the burger giant. Read more"
        },
        {
          "title": "News Details",
          "url": "https://www.irwendys.com/news/news-details/2025/THE-WENDYS-COMPANY-LAUNCHES-PROJECT-FRESH-A-STRATEGIC-PLAN-TO-DRIVE-GROWTH-AND-ENHANCE-VALUE-CREATION/default.aspx",
          "snippet": "The Wendy's Company - Investor Relations https://www.irwendys.com \u203a news \u203a news-details \u203a 2025"
        },
        {
          "title": "Wendy's doubles down on marketing effectiveness as part ...",
          "url": "https://www.marketingdive.com/news/wendys-invests-marketing-effectiveness-part-of-turnaround-plan/805114/",
          "snippet": "Nov 10, 2025 \u2014 A key goal of Wendy's recently unveiled turnaround plan is positioning the brand as \u201cthe freshest and highest-quality choice in QSR ... Read more"
        },
        {
          "title": "Wendy's Launches 'Project Fresh' Strategy to Reignite ...",
          "url": "https://www.qsrmagazine.com/story/wendys-launches-project-fresh-strategy-to-reignite-growth-and-rebuild-brand-relevance/",
          "snippet": "Oct 9, 2025 \u2014 The response was to simplify the marketing calendar in the back half of 2025 , remove broad promotions in favor of more targeted efforts within\u00a0... Read more"
        },
        {
          "title": "Wendy's Responds to Trian, Reaffirms Project Fresh Strategy",
          "url": "https://www.theglobeandmail.com/investing/markets/stocks/WEN/pressreleases/317128/wendys-responds-to-trian-reaffirms-project-fresh-strategy/",
          "snippet": "Feb 19, 2026 \u2014 Wendy's reiterated that it is pressing ahead with its Project Fresh turnaround plan, which was highlighted on its recent fourth-quarter 2025 ... Read more"
        }
      ]
    },
    "campaigns": {
      "query": "Wendy's advertising campaign Canada 2025 2026",
      "count": 5,
      "results": [
        {
          "title": "Canada Fall Flavours",
          "url": "https://www.wendys.com/blog/wendys-canada-fall-flavours",
          "snippet": "Oct 28, 2025 \u2014 October 28, 2025 . Canada Bull's-Eye BBQ Cheeseburger. Canadians have new reasons to cozy up with Wendy's \u00ae Canada . Wendy's just dropped not one\u00a0... Read more"
        },
        {
          "title": "Wendy's\u00ae Celebrates 50 Fresh Years in Canada",
          "url": "https://www.wendys.com/blog/wendys-celebrates-50-fresh-years-canada",
          "snippet": "May 20, 2025 \u2014 This year marks a significant milestone for Wendy's Canada as we proudly celebrate 50 years of serving Canadian customers. Read more"
        },
        {
          "title": "Wendy's Celebrates 50 Fresh Years in Canada",
          "url": "https://www.irwendys.com/news/news-details/2025/Wendys-Celebrates-50-Fresh-Years-in-Canada/default.aspx#:~:text=The%20brand%20prides%20itself%20on,greenhouse%2Dgrown%20lettuce%20and%20tomatoes.",
          "snippet": ""
        },
        {
          "title": "The (un)OFFICIAL @Wendy's Jingle #wendys #burgers ... - YouTube",
          "url": "https://www.youtube.com/shorts/o1-rkO18Lvs",
          "snippet": ""
        },
        {
          "title": "Wendy's\u00ae Celebrates 50 Fresh Years in Canada",
          "url": "https://www.wendys.com/blog/wendys-celebrates-50-fresh-years-canada#:~:text=Since%20opening%20our%20first%20Canadian,franchise%2Downed%20and%20locally%20operated.",
          "snippet": ""
        }
      ]
    },
    "news": {
      "query": "Wendy's Canadian QSR Canada news expansion 2025 2026",
      "count": 5,
      "results": [
        {
          "title": "Wendy's Grows Urban Footprint in Major Canadian Cities",
          "url": "https://retail-insider.com/retail-insider/2025/12/wendys-grows-urban-footprint-in-major-canadian-cities/",
          "snippet": "Dec 10, 2025 \u2014 Wendy's expands its urban presence in Canada with new downtown locations in Toronto, Montreal, and Vancouver, introducing modern restaurant\u00a0..."
        },
        {
          "title": "Wendy's Calls 2026 a Rebuilding Year as Sales Slide and ...",
          "url": "https://www.qsrmagazine.com/story/wendys-calls-2026-a-rebuilding-year-as-sales-slide-and-closures-accelerate/",
          "snippet": "Feb 13, 2026 \u2014 Wendy's interim CEO Ken Cook made it clear to investors Friday that 2026 will be a rebuilding year for the burger giant. Read more"
        },
        {
          "title": "Wendy's Continues Quebec Growth with Ongoing Urban ...",
          "url": "https://whatnow.com/montreal/restaurants/wendys-continues-quebec-growth-with-ongoing-urban-expansion/",
          "snippet": "Dec 11, 2025 \u2014 The company recently reached its 25th location in Quebec and plans to more than double its footprint in the province to 50 restaurants by\u00a0..."
        },
        {
          "title": "The Wendy's Company - Wikipedia",
          "url": "https://en.wikipedia.org/wiki/The_Wendy%27s_Company#:~:text=The%20Wendy's%20Company%20is%20an,the%20franchisor%20of%20Wendy's%20restaurants.",
          "snippet": ""
        },
        {
          "title": "Wendy's Celebrates 50 Fresh Years in Canada",
          "url": "https://www.irwendys.com/news/news-details/2025/Wendys-Celebrates-50-Fresh-Years-in-Canada/default.aspx#:~:text=The%20brand%20prides%20itself%20on,greenhouse%2Dgrown%20lettuce%20and%20tomatoes.",
          "snippet": "The Wendy's Company - Investor Relations https://www.irwendys.com \u203a news \u203a news-details \u203a 2025"
        }
      ]
    }
  },
  "pages": [
    {
      "url": "https://www.qsrmagazine.com/story/wendys-calls-2026-a-rebuilding-year-as-sales-slide-and-closures-accelerate/",
      "title": "Wendy\u2019s Calls 2026 a Rebuilding Year as Sales Slide and Closures Accelerate - QSR Magazine",
      "content": "Wendy\u2019s interim CEO Ken Cook made it clear to investors Friday that 2026 will be a rebuilding year for the burger giant.\nU.S. same-store sales fell 11.3 percent in Q4, driven by a decrease in traffic, partially offset by a higher average check. The brand attributed downward sales to significantly less marketing spend, a tough lap against the chain\u2019s SpongeBob SquarePants collaboration in Q4 2024, and a decision to move its chicken sandwich launch into 2026. One positive was the\nrollout of chicken tenders and sauces\n, which led to high customer satisfaction scores.\n\u201cWhile results were in line with our expectations, we know that we have a lot of work to do to improve performance,\u201d Cook said during Wendy\u2019s Q4 earnings call.\nTo right the ship, Wendy\u2019s is doubling down on Project Fresh, the strategic framework introduced in October that focuses on revitalizing the brand, closing underperforming restaurants, strengthening operations, and reallocating capital.\nWendy\u2019s previously announced during its Q3 earnings call in November that hundreds of U.S. units would shutter.\nThe brand anticipates 5 to 6 percent of U.S. restaurants to close, which will number in the hundreds. The cleanup includes the 28 units that shut down in the fourth quarter. The rest will come during the first half of 2026. Cook added that the closures will have a 4 percent negative impact on global systemwide sales and a $15 million to $20 million drag on adjusted EBITDA for the full year.\nThe brand finished Q4 with 5,969 U.S. locations.\n\u201cBy closing consistently underperforming restaurants, we are enabling our franchisee partners to increase focus on locations with the greatest potential for profitable growth,\u201d Cook said. \u201cSince we announced this program in November, we have been working with our franchisees to evaluate restaurants on a store-by-store basis and make collaborative decisions to optimize performance across the U.S. system as one Wendy\u2019s.\u201d\nREAD MORE\n:\nWendy\u2019s to Close Hundreds of Restaurants as Part of Greater Turnaround Strategy\nWendy\u2019s Launches \u2018Project Fresh\u2019 Strategy to Reignite Growth and Rebuild Brand Relevance\nWendy\u2019s Keeps Growth in Sight as Consumer Challenges Persist\nFor the existing footprint, the chain signaled it\u2019s open for change, including some franchisees moving away from breakfast.\n\u201cWhile many restaurants perform well at breakfast, we recognize it may not work in every restaurant as certain markets have customer dynamics that do not support a thriving breakfast business,\u201d Cook said.\nThe CEO positioned it as a move to improve franchisee profitability. Wendy\u2019s wants to give operators the flexibility to reallocate resources toward parts of the day that make the most impact. For instance, late night was the best-performing daypart in 2025.\n\u201cBreakfast remains an important daypart for the system,\u201d Cook said. \u201cThe large majority of the system is going to stay in breakfast. We\u2019re not pulling out. We\u2019re working with franchisees right now to finalize those exact numbers, and we\u2019ll share updates as we go along. This is really a common sense decision, taking learnings from the past six years that we\u2019ve been in breakfast plus taking into consideration the current environment.\u201d\nIn addition to closures, Wendy\u2019s kicked off its comeback strategy by gleaning insights from a consumer segmentation study completed in partnership with Creed UnCo, a consultancy firm led by Greg Creed, former CEO of Taco Bell and Yum! Brands.\nFirst, the brand realized a large portion of guests visit Wendy\u2019s for an everyday quality upgrade, especially with hamburgers. Cook admits the chain missed the mark in 2025, considering there was no hamburger innovation. The brand will resolve that quickly this year with the upcoming release of the Cheesy Bacon Cheeseburger. That\u2019s the start of \u201cseveral premium hamburger LTOs\u201d scheduled for 2026. Wendy\u2019s also plans to differentiate itself with a new Chicken Tender Ranch Wrap rolling out next week and the aforementioned launch of a new chicken sandwich\u2014classic and spicy\u2014that will roll out in a couple of months.\nAdditionally, Wendy\u2019s discovered many guests use it for snacking occasions. On Monday, the brand will bring back its Girl Scout Thin Mint Frosty, which performed well in 2025, and it will also incorporate \u201csweet and savory dynamics\u201d in its upcoming March Madness campaign. Also, in January, the company unveiled the new Biggie Deals platform, with $4, $6, and $8 tiers. The new, permanent offering gives customers options; they can either buy a snack-sized meal at the entry level price point or move into the higher levels if they want abundance.\nThe chain also uncovered that a large percentage of visits aren\u2019t planned. To Cook, this \u201chighlighted the importance to us to keep Wendy\u2019s top of mind and make sure we\u2019re in the consideration set.\u201d In response, Wendy\u2019s has significantly increased its social activity to drive awareness and plans to take greater advantage of culturally relevant moments.\nEqually important are the areas where Wendy\u2019s plans to pull back. The company acknowledged that promotions geared toward \u201cadventurous eaters\u201d and niche flavor profiles do not strongly resonate with its core customer base, and it will shift focus away from those efforts. That helps explain why last year\u2019s Takis collaboration, designed to attract younger consumers, fell short of expectations in both sales and traffic.\n\u201cWhat we\u2019ve learned helps us,\u201d Cook said. \u201cTarget the customer segments we want to win with, and it helps us be more relevant to them in terms of the menu choices we make, the messaging, and the operations.\u201d\nCook wants to tighten operations as well. Next year, Wendy\u2019s will continue expanding its field operations team to provide additional support to franchisees, while rolling out new software upgrades to kitchen order screens to streamline food preparation. The chain has also completed an initiative to modernize its restaurant technology architecture, enabling the company to produce innovation quicker and more efficiently.\nWendy\u2019s looks to its company-operated fleet as the gold standard, which implemented enhanced employee training, performance management plans to ensure stores were focused on the right objectives, and greater accountability measures to keep restaurants on a consistent path. Wendy\u2019s activated these improvements in early 2025, and saw results over time. Corporate restaurant same-store sales outperformed the system by 310 basis points last year. Also, overall satisfaction was up 370 basis points year-over-year in Q4 and accuracy, friendliness, and taste grew over 300 basis points.\nTwenty percent of franchisees have fully adopted the program, and the brand is working to extend the framework to the rest of the footprint. Wendy\u2019s expects changes to take hold in the second half of 2026.\n\u201cAlso, remember, we keep pushing our company-operated restaurants to continue to get better, right?\u201d Cook said. \u201cThere\u2019s no finish line here. We want to get a little bit better every single day. We want to have some healthy competition in the system and see where we end up.\u201d\nThe final pillar of Project Fresh is capital allocation, which involves Wendy\u2019s redirecting funds into areas that drive AUV, like technology that improves workflow and digital infrastructure investments that support effective marketing.\n\u201cWhile turnarounds take time, we\u2019re making bold decisions together as one Wendy\u2019s that will create a better future for all stakeholders,\u201d Cook said.\nInternationally, same-store sales fell 2 percent in Q4, but rose 1.3 percent in fiscal 2025. The chain finished the year with 1,428 international restaurants.\nFast Food\n,\nFinance\n,\nStory\n,\nWendy's",
      "source_title": "Wendy's Calls 2026 a Rebuilding Year as Sales Slide and ..."
    },
    {
      "url": "https://www.irwendys.com/news/news-details/2025/THE-WENDYS-COMPANY-LAUNCHES-PROJECT-FRESH-A-STRATEGIC-PLAN-TO-DRIVE-GROWTH-AND-ENHANCE-VALUE-CREATION/default.aspx",
      "title": "\n\tThe Wendy's Company - THE WENDY'S COMPANY LAUNCHES \"PROJECT FRESH,\" A STRATEGIC PLAN TO DRIVE GROWTH AND ENHANCE VALUE CREATION\n",
      "content": "View All News\nTHE WENDY'S COMPANY LAUNCHES \"PROJECT FRESH,\" A STRATEGIC PLAN TO DRIVE GROWTH AND ENHANCE VALUE CREATION\nOctober 9, 2025\nDownload\n(opens in new window)\nStrengthening Wendy's brand positioning strategy to reach consumers more effectively\nAssessing U.S. restaurant system to increase profitability\nTransforming U.S. restaurant operations to elevate experience and drive greater efficiency\nReallocating capital and resources to drive profitable growth\nDUBLIN, Ohio\n,\nOct. 9, 2025\n/PRNewswire/ -- The Wendy's Company (Nasdaq: WEN) (\"Wendy's\" or the \"Company\") today unveiled\nProject Fresh\n, a comprehensive strategic plan designed to revitalize the brand, reignite growth, accelerate profitability across the Wendy's system and enhance shareholder value.\n\"Wendy's Board of Directors and management team are dissatisfied with the current valuation of the Company and have been working to put the Company on the right path to create value for our franchisees, employees and shareholders,\" said Chairman of the Board, Art Winkleblack. \"Execution is underway and we are confident that\nProject Fresh\nwill position Wendy's as the industry leader\u2014one that guests love, franchisees are proud to operate, teams are excited to be a part of, and creates significant value for our shareholders.\"\n\"Wendy's is a brand built on quality, authenticity and innovation,\" said Ken Cook, Interim Chief Executive Officer and Chief Financial Officer.\u00a0\"With\nProject Fresh\n, we're taking decisive steps together as\nOne Wendy's\nto strengthen our foundation, enhance restaurant performance and modernize how our customers experience the brand.\nProject Fresh\nis about reigniting the energy and distinctiveness that have always made Wendy's special, while positioning the Company and our franchisees for profitable growth.\"\nGrounded in a stronger franchisee partnership under the\nOne Wendy's\napproach, the\nProject Fresh\nplan is expected to provide a clear roadmap centered across four core pillars: brand revitalization, system optimization, operational excellence and a reallocation of capital and resources to drive profitable growth. Together, these initiatives will redefine how Wendy's operates, invests and engages with customers to create long-term value.\nKey actions across\nProject Fresh\nto drive growth and profitability include:\nBrand revitalization:\nStrengthening brand positioning by leveraging Wendy's rich heritage of quality, innovation and unique voice to connect across all touchpoints with the next generation of customers. We have retained leading industry consultancy Creed UnCo, led by Greg Creed, former CEO of Taco Bell and Yum! Brands, to assist in transforming our marketing effectiveness based on data-driven, needs-based customer segmentation analyses to improve relevance, ease and distinctiveness of the Wendy's brand.\nSystem optimization:\nReallocating resources to prioritize AUV growth in the U.S. with the goal of achieving industry-leading restaurant performance. This includes optimizing labor and operating hours across dayparts, partnering closely with franchisees to maximize profitability within each market, leveraging insights from Company-operated restaurants and adopting a returns-based approach to franchisee investments. Internationally, capital will continue to be deployed efficiently to sustain strong net unit growth and we remain encouraged by our growth trajectory, recent market entries and our significant international opportunities.\nOperational excellence:\nIncreasing investments to enhance the customer experience in restaurants through hospitality, digital and equipment efficiency, simplified processes, labor and technology and enhanced training.\nCapital allocation:\nOptimizing capital expenditures to align with our near-term priority to drive AUV growth in the U.S. Changes include the reduction of capital allocated to the Build to Suit program by approximately $20 million in 2025 and a larger anticipated reduction in 2026, allowing Wendy's to invest more in areas to drive AUV growth, including technology and marketing. The Company is also working with an independent financial advisor to identify additional opportunities to optimize its capital allocation. The Company remains committed to its dividend and returning capital to shareholders, supported by its strong free cash flow generation.\nWinkleblack added, \"The Board continues to work diligently on the CEO selection process. We are working with a leading global executive search firm and are carefully evaluating internal and external candidates to ensure the strongest leadership to guide the Company through its next phase of growth. The Board remains focused on advancing the Company's strategic priorities in close collaboration with interim CEO, Ken Cook. The Board will take the time necessary for this process and is targeting completion by the end of the year.\"\nThe Company will provide further detail about these initiatives when it releases its third quarter results on November 7, 2025.\nForward-Looking Statements\nThis release contains certain statements that are \"forward-looking statements\" within the meaning of the Private Securities Litigation Reform Act of 1995 (the \"Reform Act\"). Generally, forward-looking statements include the words \"may,\" \"believes,\" \"plans,\" \"expects,\" \"anticipates,\" \"intends,\" \"estimate,\" \"goal,\" \"upcoming,\" \"outlook,\" \"guidance\" or the negation thereof, or similar expressions. In addition, all statements regarding the impact or results of our\nProject Fresh\ninitiatives, or those that address future operating, financial or business performance, strategies or initiatives, future efficiencies or savings, anticipated costs or charges, future capitalization, anticipated impacts of recent or pending investments or transactions, and statements expressing general views about future results or brand health, are forward-looking statements within the meaning of the Reform Act. Forward-looking statements are based on the Company's expectations at the time such statements are made, speak only as of the dates they are made and are susceptible to a number of risks, uncertainties and other factors. For all such forward-looking statements, the Company claims the protection of the safe harbor for forward-looking statements contained in the Reform Act. The Company's actual results, performance and achievements may differ materially from any future results, performance or achievements expressed or implied by the Company's forward-looking statements.\nMany important factors could affect the Company's future results and cause those results to differ materially from those expressed in or implied by the Company's forward-looking statements. Such factors include, but are not limited to, the following: (1) the impact of competition or poor customer experiences at Wendy's restaurants; (2) adverse economic conditions or disruptions, including in regions with a high concentration of Wendy's restaurants; (3) changes in discretionary consumer spending and consumer tastes and preferences; (4) impacts to the Company's corporate reputation or the value and perception of the Company's brand; (5) the effectiveness of the Company's marketing and advertising programs and new product development; (6) the Company's ability to manage the impact of social or digital media; (7) the Company's ability to protect its intellectual property; (8) food safety events or health concerns involving the Company's products; (9) our ability to deliver global sales growth and maintain or grow market share across our\u00a0dayparts; (10) the Company's ability to achieve its growth strategy through new restaurant development; (11) the Company's ability to effectively manage the acquisition and disposition of restaurants or successfully implement other strategic initiatives; (12) risks associated with leasing and owning significant amounts of real estate, including environmental matters; (13) risks associated with the Company's international operations, including the ability to execute its international growth strategy; (14) changes in commodity and other operating costs; (15) shortages or interruptions in the supply or distribution of the Company's products and other risks associated with the Company's independent supply chain purchasing co-op; (16) the impact of increased labor costs or labor shortages; (17) the continued succession and retention of key personnel and the effectiveness of the Company's leadership and organizational structure; (18) risks associated with the Company's digital commerce strategy, platforms and technologies, including its ability to adapt to changes in industry trends and consumer preferences; (19) the Company's dependence on computer systems and information technology, including risks associated with the failure or interruption of its systems or technology or the occurrence of cyber incidents or deficiencies; (20) risks associated with the Company's securitized financing facility and other debt agreements, including compliance with operational and financial covenants, restrictions on its ability to raise additional capital, the impact of its overall debt levels and the Company's ability to generate sufficient cash flow to meet its debt service obligations and operate its business; (21) risks associated with the Company's capital allocation policy, including the amount and timing of equity and debt repurchases and dividend payments; (22) risks associated with complaints and litigation, compliance with legal and regulatory requirements and an increased focus on environmental, social and governance issues; (23) risks associated with the availability and cost of insurance, changes in accounting standards, the recognition of impairment or other charges, changes in tax rates or tax laws and fluctuations in foreign currency exchange rates; (24) conditions beyond the Company's control, such as adverse weather conditions, natural disasters, hostilities, social unrest, health epidemics or pandemics or other catastrophic events; (25) risks associated with the Company's predominantly franchised business model; and (26) other risks and uncertainties cited in the Company's releases, public statements and/or filings with the Securities and Exchange Commission, including those identified in the \"Risk Factors\" sections of the Company's Forms 10-K and 10-Q.\nAll future written and oral forward-looking statements attributable to the Company or any person acting on its behalf are expressly qualified in their entirety by the cautionary statements contained or referred to above. New risks and uncertainties arise from time to time, and factors that the Company currently deems immaterial may become material, and it is impossible for the Company to predict these events or how they may affect the Company.\nThe Company assumes no obligation to update any forward-looking statements after the date of this release as a result of new information, future events or developments, except as required by federal securities laws, although the Company may do so from time to time. The Company does not endorse any projections regarding future performance that may be made by third parties.\nAbout Wendy's\nWendy's\n\u00ae\nwas founded in 1969 by Dave Thomas in Columbus, Ohio. Dave built his business on the premise, \"Quality is our Recipe\n\u00ae\n,\" which remains the guidepost of the Wendy's system. Wendy's is best known for its made-to-order square hamburgers, using fresh, never frozen beef*, freshly-prepared salads, and other signature items like chili, baked potatoes and the Frosty\n\u00ae\ndessert.\u00a0The Wendy's Company (Nasdaq: WEN) is committed to doing the right thing and making a positive difference in the lives of others.\u00a0This is most visible through the Company's support of the Dave Thomas Foundation for Adoption\u00ae and its signature Wendy's Wonderful Kids\n\u00ae\nprogram, which seeks to find a loving, forever home for every child waiting to be adopted from the North American foster care system.\u00a0Today, Wendy's and its franchisees employ hundreds of thousands of people across over 7,000 restaurants worldwide with a vision of becoming the world's most thriving and beloved restaurant brand. For details on franchising, connect with us at\nwww.wendys.com/franchising\n.\nVisit\nwww.wendys.com\nand\nwww.squaredealblog.com\nfor more information and connect with us on X and Instagram using @wendys, and on Facebook at\nwww.facebook.com/wendys\n.\n*Fresh beef available in the contiguous U.S., Alaska, and Canada.\nMedia Contact\n:\nHeidi Schauer\nVice President \u2013 Communications, Public Affairs & Customer Care\n(614) 764-3368;\nheidi.schauer@wendys.com\nInvestor Contact\n:\nAaron Broholm\nHead of Investor Relations\n(614) 764-3345;\naaron.broholm@wendys.com\nView original content to download multimedia:\nhttps://www.prnewswire.com/news-releases/the-wendys-company-launches-project-fresh-a-strategic-plan-to-drive-growth-and-enhance-value-creation-302578985.html\nSOURCE The Wendy\u2019s Company\nView All News",
      "source_title": "News Details"
    },
    {
      "url": "https://www.marketingdive.com/news/wendys-invests-marketing-effectiveness-part-of-turnaround-plan/805114/",
      "title": "Wendy\u2019s doubles down on marketing effectiveness as part of turnaround | Marketing Dive",
      "content": "An article from\nWendy\u2019s doubles down on marketing effectiveness as part of turnaround\nThe QSR\u2019s partnership with consultant Creed UnCo\u00a0aims to clarify what drives purchasing decisions and refine messaging around value.\nPublished Nov. 10, 2025\nPeter Adams\nSenior Reporter\nShare\nCopy link\nEmail\nLinkedIn\nX/Twitter\nFacebook\nPrint\nLicense\nAdd us on Google\nA key goal of Wendy\u2019s recently unveiled turnaround plan is positioning the brand as \u201cthe freshest and highest-quality choice in QSR,\u201d according to CFO and interim CEO Ken Cook.\nBrandon Bell / Staff via Getty Images\nListen to the article\n3 min\nThis audio is auto-generated. Please let us know if you have\nfeedback\n.\nWendy\u2019s is putting a bigger focus on data-driven marketing amid a push to restore brand relevance and bounce back from a stretch of flagging financial performance. The Frosty maker\u2019s same-restaurant sales, an important measure of QSR health, slid 4.7% year over year in the U.S. to around $3 billion in Q3,\naccording to an earnings statement\n, dragging results down.\nWhile Wendy\u2019s U.S. business experienced falling traffic for the period ended Sept. 28, digital sales rose 14.9% YoY, accounting for 20.3% of sales overall, an all-time company high. Executives from the QSR also offered further details on their vision for Project Fresh, a turnaround plan\nfirst announced in early October\n, during a call\ndiscussing the Q3 results with investors late last week\n.\n\u201cThe first pillar of Project Fresh is revitalizing the Wendy\u2019s brand,\u201d said Ken Cook, Wendy\u2019s CFO and interim CEO, on the call. \u201cThis is about positioning Wendy\u2019s as the freshest and highest-quality choice in QSR by celebrating what makes us stand out from the competition.\u201d\nOne of the chief aims of Project Fresh is winning over new customers to Wendy\u2019s through \u201ccompelling marketing,\u201d per Cook. Recent promotions oriented around value, such as an $8 meal deal, drove repeat purchases among existing diners, but fell short on other measures.\n\u201cIt didn\u2019t do as good of a job as we wanted attracting new customers,\u201d said Cook. \u201cSo that tells me we have an opportunity to tell our value story in a different way by focusing on both price and the quality of the ingredients we get.\u201d\nProject Fresh entails shifting investment from build-to-suit development programs toward technology and marketing effectiveness initiatives that can support average volume unit growth. Technology improvements include souping up back-of-house systems, like the screens employees use to build sandwich orders, with an eye toward efficiency. On the marketing effectiveness front, Wendy\u2019s has partnered with consultancy Creed UnCo to dig into customer insights that will improve precision and contribute to long-term brand building.\nCreed UnCo, which was founded by former Yum Brands CEO Greg Creed, since last month has been helping Wendy\u2019s run a customer segmentation study that \u201cwill clarify which attributes drive [customer] purchasing decisions and help us refine how we deliver and communicate value across every touch point,\u201d said Cook, who has\nserved as interim CEO since Kirk Tanner departed the chain last summer\n.\nKeep up with the story. Subscribe to the Marketing Dive free daily newsletter\nEmail:\nSelect Newsletter:\nDaily Dive\nM-F\nSelect Newsletter:\nMobile Weekly\nEvery Thursday\nSelect Newsletter:\nAgencies Weekly\nEvery Monday\nSelect user consent:\nBy signing up to receive our newsletter, you agree to our\nTerms of Use\nand\nPrivacy Policy\n. You can unsubscribe at anytime.\nSign up\nA valid email address is required.\nPlease select at least one newsletter.\nAs with many turnaround strategies, Wendy\u2019s still has to undergo some potentially painful pruning. Cook estimated that \u201caround a mid-single-digit percentage of U.S. restaurants\u201d could end up closing as Wendy\u2019s shutters underperforming locations.\nWendy\u2019s for years was known for its combative marketing streak,\nembodied in a sassy social media presence\nthat was unafraid to dig into rivals. But the marketing needs of the QSR category changed quickly during the pandemic and are again evolving as\nmacroeconomic pressures put the messaging emphasis back on value\n. Recent Wendy\u2019s campaigns of note include a collaboration with Netflix\u2019s hit series \u201cWednesday\u201d\non a limited-time goth-themed meal and mobile game\n.\nRecommended Reading\nMcDonald\u2019s Extra Value Meals insulated sales from diner price sensitivity\nRestaurant Dive\nWendy\u2019s marketing embraces the macabre with \u2018Wednesday\u2019 collaboration\nBy\nPeter Adams\n\u2022\nJuly 23, 2025\nAdd us on Google\nShare\nCopy link\nEmail\nLinkedIn\nX/Twitter\nFacebook\nPrint\npurchase licensing rights\nFiled Under:\nBrand Strategy,\nData/Analytics",
      "source_title": "Wendy's doubles down on marketing effectiveness as part ..."
    }
  ]
}